pg_temp/__init__.py
pg_temp/pg_temp.py
pg_temp/version.py
pg_temp-0.9.1.dist-info/LICENSE
pg_temp-0.9.1.dist-info/METADATA
pg_temp-0.9.1.dist-info/WHEEL
pg_temp-0.9.1.dist-info/top_level.txt
pg_temp-0.9.1.dist-info/RECORD
