Metadata-Version: 2.1
Name: pg-temp
Version: 0.9.1
Summary: Quickly create Postgres databases, e.g. for testing
Home-page: https://github.com/ugtar/pg_temp
Author: Uri Okrent
Author-email: uokrent@gmail.com
License: MIT
Keywords: postgres,testing
Platform: POSIX
Classifier: License :: OSI Approved :: BSD License
Classifier: Operating System :: OS Independent
Classifier: Programming Language :: Python :: 3.6
Classifier: Programming Language :: Python :: 3.7
Classifier: Programming Language :: Python :: 3.8
Classifier: Programming Language :: Python :: 3.9
Classifier: Topic :: Software Development :: Libraries :: Python Modules
Classifier: Development Status :: 5 - Production/Stable
Classifier: Intended Audience :: Developers
Classifier: Programming Language :: Python
Requires-Python: >=3.5
License-File: LICENSE
